kendrick_package/__init__.py
kendrick_package/example.py
kendrick_package/genai_utils.py
kendrick_package-0.0.2.dist-info/LICENSE
kendrick_package-0.0.2.dist-info/METADATA
kendrick_package-0.0.2.dist-info/WHEEL
kendrick_package-0.0.2.dist-info/top_level.txt
kendrick_package-0.0.2.dist-info/RECORD
