Metadata-Version: 2.2
Name: kendrick_package
Version: 0.0.2
Summary: A helpful package for Kendrick
Author-email: Kendrick99 <kendrickph4m@gmail.com>
Project-URL: Homepage, https://github.com/m1np3m/kendrick_utils
Project-URL: Issues, https://github.com/m1np3m/kendrick_utils/issues
Classifier: Programming Language :: Python :: 3
Classifier: Operating System :: OS Independent
Classifier: License :: OSI Approved :: MIT License
Requires-Python: >=3.8
License-File: LICENSE
Requires-Dist: streamlit>=1.21.0
Requires-Dist: openai>=1.21.0
Requires-Dist: numpy==1.26.4
Requires-Dist: llama-index==0.12.16
Requires-Dist: llama-index-agent-openai==0.4.1
Requires-Dist: llama-index-core==0.12.22
Requires-Dist: llama-index-embeddings-huggingface==0.4.0
Requires-Dist: llama-index-embeddings-huggingface-optimum==0.3.0
Requires-Dist: llama-index-embeddings-openai==0.3.1
